neogc/__init__.py
neogc/__main__.py
neogc/config.py
neogc/main.py
neogc/version.py
neogc-0.1.1.dist-info/METADATA
neogc-0.1.1.dist-info/WHEEL
neogc-0.1.1.dist-info/entry_points.txt
neogc-0.1.1.dist-info/RECORD
