Metadata-Version: 2.4
Name: neogc
Version: 0.1.1
Summary: 
Author: Igor DC
Author-email: igordcard@gmail.com
Requires-Python: >=3.13
Classifier: Programming Language :: Python :: 3
Classifier: Programming Language :: Python :: 3.13
Classifier: Programming Language :: Python :: 3.14
Requires-Dist: typer (>=0.19.2,<0.20.0)
